{
  "name": "randomstring",
  "type": "flogo:activity",
  "ref": "https://github.com/carlskii/randomstring",
  "version": "0.0.1",
  "title": "Random String",
  "description": "Creates a random string consisting with the length you specify",
  "author": "retgits",
  "homepage": "https://github.com/carlskii/randomstring/blob/master/activity.json",
  "inputs":[
    {
      "name": "length",
      "type": "integer"
    }
  ],
  "outputs": [
    {
      "name": "result",
      "type": "string"
    }
  ]
}
